cubizoid/__init__.py
cubizoid/cli.py
cubizoid/common.py
cubizoid/plugins/__init__.py
cubizoid/plugins/embed.py
cubizoid/plugins/replicate.py
kube_tools_kferrone-1.0.2.dist-info/METADATA
kube_tools_kferrone-1.0.2.dist-info/WHEEL
kube_tools_kferrone-1.0.2.dist-info/entry_points.txt
kube_tools_kferrone-1.0.2.dist-info/top_level.txt
kube_tools_kferrone-1.0.2.dist-info/RECORD
