Metadata-Version: 2.1
Name: kube-tools-kferrone
Version: 1.0.2
Summary: Useful tools for manipulating Kubernetes manifests
Home-page: https://github.com/Cubizoid/kube-tools
Author: Kelly Ferrone
Author-email: 4399427+kferrone@users.noreply.github.com
License: UNKNOWN
Project-URL: Bug Tracker, https://github.com/Cubizoid/kube-tools/issues
Platform: UNKNOWN
Classifier: Programming Language :: Python :: 3
Classifier: License :: OSI Approved :: MIT License
Classifier: Operating System :: OS Independent
Requires-Python: >=3.6
